rsk/__init__.py
rsk/api.py
rsk/backend.py
rsk/client.py
rsk/config.py
rsk/constants.py
rsk/control.py
rsk/debug.sh
rsk/detection.py
rsk/dumb_ia.py
rsk/dump_referee.py
rsk/em.py
rsk/field.py
rsk/game_controller.py
rsk/kinematics.py
rsk/logger.py
rsk/packets.py
rsk/path_finder.py
rsk/path_finding.py
rsk/place.py
rsk/referee.py
rsk/robot.py
rsk/robot_serial.py
rsk/robot_wifi.py
rsk/robots.py
rsk/simulator.py
rsk/state.py
rsk/tasks.py
rsk/utils.py
rsk/video.py
rsk/static/camera-setting.html
rsk/static/favicon.ico
rsk/static/index.html
rsk/static/referee_event_neutral.html
rsk/static/referee_event_team.html
rsk/static/robot.html
rsk/static/scheduler_team.html
rsk/static/team.html
rsk/static/bootstrap/css/bootstrap-grid.css
rsk/static/bootstrap/css/bootstrap-grid.css.map
rsk/static/bootstrap/css/bootstrap-grid.min.css
rsk/static/bootstrap/css/bootstrap-grid.min.css.map
rsk/static/bootstrap/css/bootstrap-grid.rtl.css
rsk/static/bootstrap/css/bootstrap-grid.rtl.css.map
rsk/static/bootstrap/css/bootstrap-grid.rtl.min.css
rsk/static/bootstrap/css/bootstrap-grid.rtl.min.css.map
rsk/static/bootstrap/css/bootstrap-reboot.css
rsk/static/bootstrap/css/bootstrap-reboot.css.map
rsk/static/bootstrap/css/bootstrap-reboot.min.css
rsk/static/bootstrap/css/bootstrap-reboot.min.css.map
rsk/static/bootstrap/css/bootstrap-reboot.rtl.css
rsk/static/bootstrap/css/bootstrap-reboot.rtl.css.map
rsk/static/bootstrap/css/bootstrap-reboot.rtl.min.css
rsk/static/bootstrap/css/bootstrap-reboot.rtl.min.css.map
rsk/static/bootstrap/css/bootstrap-utilities.css
rsk/static/bootstrap/css/bootstrap-utilities.css.map
rsk/static/bootstrap/css/bootstrap-utilities.min.css
rsk/static/bootstrap/css/bootstrap-utilities.min.css.map
rsk/static/bootstrap/css/bootstrap-utilities.rtl.css
rsk/static/bootstrap/css/bootstrap-utilities.rtl.css.map
rsk/static/bootstrap/css/bootstrap-utilities.rtl.min.css
rsk/static/bootstrap/css/bootstrap-utilities.rtl.min.css.map
rsk/static/bootstrap/css/bootstrap.css
robot_soccer_kit-2.4.2.dist-info/LICENSE
robot_soccer_kit-2.4.2.dist-info/METADATA
robot_soccer_kit-2.4.2.dist-info/WHEEL
robot_soccer_kit-2.4.2.dist-info/top_level.txt
robot_soccer_kit-2.4.2.dist-info/RECORD
