Metadata-Version: 2.1
Name: robot-soccer-kit
Version: 2.4.2
Summary: Robot Soccer Kit
Home-page: https://github.com/rhoban/robot-soccer-kit/
Author: Rhoban team
Author-email: team@rhoban.com
License: UNKNOWN
Keywords: robot holonomic omniwheel ssl sct robocup junior soccer standard localized tracking
Platform: UNKNOWN
Classifier: Programming Language :: Python :: 3
Classifier: License :: Free for non-commercial use
Classifier: Operating System :: OS Independent
Requires-Python: >=3.6
License-File: LICENSE
Requires-Dist: astar
Requires-Dist: numpy
Requires-Dist: pyyaml
Requires-Dist: pyzmq
Provides-Extra: gc
Requires-Dist: flask ; extra == 'gc'
Requires-Dist: flask-cors ; extra == 'gc'
Requires-Dist: opencv-contrib-python ; extra == 'gc'
Requires-Dist: pyserial ; extra == 'gc'
Requires-Dist: waitress ; extra == 'gc'
